normino.py
normino-11.1.dist-info/METADATA
normino-11.1.dist-info/WHEEL
normino-11.1.dist-info/entry_points.txt
normino-11.1.dist-info/top_level.txt
normino-11.1.dist-info/RECORD
