Metadata-Version: 2.4
Name: normino
Version: 11.1
Home-page: https://github.com/SLDDL/Normino
Project-URL: Documentation, https://github.com/SLDDL/Normino/blob/main/README.md
Project-URL: Source, https://github.com/SLDDL/Normino
Project-URL: Tracker, https://github.com/SLDDL/Normino/issues
Project-URL: Icon, https://raw.githubusercontent.com/SLDDL/Normino/main/icon.png
Requires-Dist: colorama
Requires-Dist: beautifulsoup4
Requires-Dist: requests
Dynamic: description
Dynamic: description-content-type
Dynamic: home-page
Dynamic: project-url
Dynamic: requires-dist
